{
  "title": "City's Lounge",
  "subtitle": "Meet, share, enjoy",
  "image": "/img/citys-park/01.jpg",
  "sectionId": "citys-lounge",
  "order": 1,
  "content": "A morning coffee, a small lunch meeting, a spontaneous evening celebration...  \nGather around a table with your friends in nature, or organize an unforgettable event under the lights.\n\nNo formality, just your rhythm, your space.",
  "locale": "en",
  "slug": "citys-lounge",
  "publishedAt": "2025-08-07T13:33:19.687Z",
  "status": "published"
}